{
  "version": "6",
  "dialect": "sqlite",
  "id": "14e0662b-a640-40b9-9c60-5def9b28a01d",
  "prevId": "00000000-0000-0000-0000-000000000000",
  "tables": {
    "account": {
      "name": "account",
      "columns": {
        "userId": {
          "name": "userId",
          "type": "text",
          "primaryKey": false,
          "notNull": true,
          "autoincrement": false
        },
        "type": {
          "name": "type",
          "type": "text",
          "primaryKey": false,
          "notNull": true,
          "autoincrement": false
        },
        "provider": {
          "name": "provider",
          "type": "text",
          "primaryKey": false,
          "notNull": true,
          "autoincrement": false
        },
        "providerAccountId": {
          "name": "providerAccountId",
          "type": "text",
          "primaryKey": false,
          "notNull": true,
          "autoincrement": false
        },
        "refresh_token": {
          "name": "refresh_token",
          "type": "text",
          "primaryKey": false,
          "notNull": false,
          "autoincrement": false
        },
        "access_token": {
          "name": "access_token",
          "type": "text",
          "primaryKey": false,
          "notNull": false,
          "autoincrement": false
        },
        "expires_at": {
          "name": "expires_at",
          "type": "integer",
          "primaryKey": false,
          "notNull": false,
          "autoincrement": false
        },
        "token_type": {
          "name": "token_type",
          "type": "text",
          "primaryKey": false,
          "notNull": false,
          "autoincrement": false
        },
        "scope": {
          "name": "scope",
          "type": "text",
          "primaryKey": false,
          "notNull": false,
          "autoincrement": false
        },
        "id_token": {
          "name": "id_token",
          "type": "text",
          "primaryKey": false,
          "notNull": false,
          "autoincrement": false
        },
        "session_state": {
          "name": "session_state",
          "type": "text",
          "primaryKey": false,
          "notNull": false,
          "autoincrement": false
        }
      },
      "indexes": {
        "account_userId_idx": {
          "name": "account_userId_idx",
          "columns": [
            "userId"
          ],
          "isUnique": false
        }
      },
      "foreignKeys": {
        "account_userId_user_id_fk": {
          "name": "account_userId_user_id_fk",
          "tableFrom": "account",
          "tableTo": "user",
          "columnsFrom": [
            "userId"
          ],
          "columnsTo": [
            "id"
          ],
          "onDelete": "cascade",
          "onUpdate": "no action"
        }
      },
      "compositePrimaryKeys": {
        "account_provider_providerAccountId_pk": {
          "columns": [
            "provider",
            "providerAccountId"
          ],
          "name": "account_provider_providerAccountId_pk"
        }
      },
      "uniqueConstraints": {},
      "checkConstraints": {}
    },
    "friend_request": {
      "name": "friend_request",
      "columns": {
        "fromUserId": {
          "name": "fromUserId",
          "type": "text",
          "primaryKey": false,
          "notNull": true,
          "autoincrement": false
        },
        "toUserId": {
          "name": "toUserId",
          "type": "text",
          "primaryKey": false,
          "notNull": true,
          "autoincrement": false
        },
        "createdAt": {
          "name": "createdAt",
          "type": "integer",
          "primaryKey": false,
          "notNull": true,
          "autoincrement": false,
          "default": "(unixepoch() * 1000)"
        }
      },
      "indexes": {
        "friend_request_to_idx": {
          "name": "friend_request_to_idx",
          "columns": [
            "toUserId"
          ],
          "isUnique": false
        }
      },
      "foreignKeys": {
        "friend_request_fromUserId_user_id_fk": {
          "name": "friend_request_fromUserId_user_id_fk",
          "tableFrom": "friend_request",
          "tableTo": "user",
          "columnsFrom": [
            "fromUserId"
          ],
          "columnsTo": [
            "id"
          ],
          "onDelete": "cascade",
          "onUpdate": "no action"
        },
        "friend_request_toUserId_user_id_fk": {
          "name": "friend_request_toUserId_user_id_fk",
          "tableFrom": "friend_request",
          "tableTo": "user",
          "columnsFrom": [
            "toUserId"
          ],
          "columnsTo": [
            "id"
          ],
          "onDelete": "cascade",
          "onUpdate": "no action"
        }
      },
      "compositePrimaryKeys": {
        "friend_request_fromUserId_toUserId_pk": {
          "columns": [
            "fromUserId",
            "toUserId"
          ],
          "name": "friend_request_fromUserId_toUserId_pk"
        }
      },
      "uniqueConstraints": {},
      "checkConstraints": {}
    },
    "friend": {
      "name": "friend",
      "columns": {
        "userId": {
          "name": "userId",
          "type": "text",
          "primaryKey": false,
          "notNull": true,
          "autoincrement": false
        },
        "friendUserId": {
          "name": "friendUserId",
          "type": "text",
          "primaryKey": false,
          "notNull": true,
          "autoincrement": false
        },
        "createdAt": {
          "name": "createdAt",
          "type": "integer",
          "primaryKey": false,
          "notNull": true,
          "autoincrement": false,
          "default": "(unixepoch() * 1000)"
        }
      },
      "indexes": {},
      "foreignKeys": {
        "friend_userId_user_id_fk": {
          "name": "friend_userId_user_id_fk",
          "tableFrom": "friend",
          "tableTo": "user",
          "columnsFrom": [
            "userId"
          ],
          "columnsTo": [
            "id"
          ],
          "onDelete": "cascade",
          "onUpdate": "no action"
        },
        "friend_friendUserId_user_id_fk": {
          "name": "friend_friendUserId_user_id_fk",
          "tableFrom": "friend",
          "tableTo": "user",
          "columnsFrom": [
            "friendUserId"
          ],
          "columnsTo": [
            "id"
          ],
          "onDelete": "cascade",
          "onUpdate": "no action"
        }
      },
      "compositePrimaryKeys": {
        "friend_userId_friendUserId_pk": {
          "columns": [
            "userId",
            "friendUserId"
          ],
          "name": "friend_userId_friendUserId_pk"
        }
      },
      "uniqueConstraints": {},
      "checkConstraints": {}
    },
    "match_player": {
      "name": "match_player",
      "columns": {
        "matchId": {
          "name": "matchId",
          "type": "text",
          "primaryKey": false,
          "notNull": true,
          "autoincrement": false
        },
        "userId": {
          "name": "userId",
          "type": "text",
          "primaryKey": false,
          "notNull": true,
          "autoincrement": false
        },
        "seat": {
          "name": "seat",
          "type": "integer",
          "primaryKey": false,
          "notNull": true,
          "autoincrement": false
        },
        "finishingPosition": {
          "name": "finishingPosition",
          "type": "integer",
          "primaryKey": false,
          "notNull": true,
          "autoincrement": false
        },
        "muBefore": {
          "name": "muBefore",
          "type": "real",
          "primaryKey": false,
          "notNull": true,
          "autoincrement": false
        },
        "sigmaBefore": {
          "name": "sigmaBefore",
          "type": "real",
          "primaryKey": false,
          "notNull": true,
          "autoincrement": false
        },
        "muAfter": {
          "name": "muAfter",
          "type": "real",
          "primaryKey": false,
          "notNull": true,
          "autoincrement": false
        },
        "sigmaAfter": {
          "name": "sigmaAfter",
          "type": "real",
          "primaryKey": false,
          "notNull": true,
          "autoincrement": false
        }
      },
      "indexes": {
        "match_player_userId_idx": {
          "name": "match_player_userId_idx",
          "columns": [
            "userId"
          ],
          "isUnique": false
        }
      },
      "foreignKeys": {
        "match_player_matchId_match_id_fk": {
          "name": "match_player_matchId_match_id_fk",
          "tableFrom": "match_player",
          "tableTo": "match",
          "columnsFrom": [
            "matchId"
          ],
          "columnsTo": [
            "id"
          ],
          "onDelete": "cascade",
          "onUpdate": "no action"
        },
        "match_player_userId_user_id_fk": {
          "name": "match_player_userId_user_id_fk",
          "tableFrom": "match_player",
          "tableTo": "user",
          "columnsFrom": [
            "userId"
          ],
          "columnsTo": [
            "id"
          ],
          "onDelete": "no action",
          "onUpdate": "no action"
        }
      },
      "compositePrimaryKeys": {
        "match_player_matchId_userId_pk": {
          "columns": [
            "matchId",
            "userId"
          ],
          "name": "match_player_matchId_userId_pk"
        }
      },
      "uniqueConstraints": {},
      "checkConstraints": {}
    },
    "match": {
      "name": "match",
      "columns": {
        "id": {
          "name": "id",
          "type": "text",
          "primaryKey": true,
          "notNull": true,
          "autoincrement": false
        },
        "startedAt": {
          "name": "startedAt",
          "type": "integer",
          "primaryKey": false,
          "notNull": true,
          "autoincrement": false
        },
        "endedAt": {
          "name": "endedAt",
          "type": "integer",
          "primaryKey": false,
          "notNull": true,
          "autoincrement": false
        },
        "winnerUserId": {
          "name": "winnerUserId",
          "type": "text",
          "primaryKey": false,
          "notNull": true,
          "autoincrement": false
        },
        "seatCount": {
          "name": "seatCount",
          "type": "integer",
          "primaryKey": false,
          "notNull": true,
          "autoincrement": false
        }
      },
      "indexes": {
        "match_winner_idx": {
          "name": "match_winner_idx",
          "columns": [
            "winnerUserId"
          ],
          "isUnique": false
        }
      },
      "foreignKeys": {
        "match_winnerUserId_user_id_fk": {
          "name": "match_winnerUserId_user_id_fk",
          "tableFrom": "match",
          "tableTo": "user",
          "columnsFrom": [
            "winnerUserId"
          ],
          "columnsTo": [
            "id"
          ],
          "onDelete": "no action",
          "onUpdate": "no action"
        }
      },
      "compositePrimaryKeys": {},
      "uniqueConstraints": {},
      "checkConstraints": {}
    },
    "mmr_history": {
      "name": "mmr_history",
      "columns": {
        "id": {
          "name": "id",
          "type": "text",
          "primaryKey": true,
          "notNull": true,
          "autoincrement": false
        },
        "userId": {
          "name": "userId",
          "type": "text",
          "primaryKey": false,
          "notNull": true,
          "autoincrement": false
        },
        "matchId": {
          "name": "matchId",
          "type": "text",
          "primaryKey": false,
          "notNull": false,
          "autoincrement": false
        },
        "muBefore": {
          "name": "muBefore",
          "type": "real",
          "primaryKey": false,
          "notNull": true,
          "autoincrement": false
        },
        "sigmaBefore": {
          "name": "sigmaBefore",
          "type": "real",
          "primaryKey": false,
          "notNull": true,
          "autoincrement": false
        },
        "muAfter": {
          "name": "muAfter",
          "type": "real",
          "primaryKey": false,
          "notNull": true,
          "autoincrement": false
        },
        "sigmaAfter": {
          "name": "sigmaAfter",
          "type": "real",
          "primaryKey": false,
          "notNull": true,
          "autoincrement": false
        },
        "createdAt": {
          "name": "createdAt",
          "type": "integer",
          "primaryKey": false,
          "notNull": true,
          "autoincrement": false,
          "default": "(unixepoch() * 1000)"
        }
      },
      "indexes": {
        "mmr_history_user_time_idx": {
          "name": "mmr_history_user_time_idx",
          "columns": [
            "userId",
            "createdAt"
          ],
          "isUnique": false
        }
      },
      "foreignKeys": {
        "mmr_history_userId_user_id_fk": {
          "name": "mmr_history_userId_user_id_fk",
          "tableFrom": "mmr_history",
          "tableTo": "user",
          "columnsFrom": [
            "userId"
          ],
          "columnsTo": [
            "id"
          ],
          "onDelete": "no action",
          "onUpdate": "no action"
        },
        "mmr_history_matchId_match_id_fk": {
          "name": "mmr_history_matchId_match_id_fk",
          "tableFrom": "mmr_history",
          "tableTo": "match",
          "columnsFrom": [
            "matchId"
          ],
          "columnsTo": [
            "id"
          ],
          "onDelete": "set null",
          "onUpdate": "no action"
        }
      },
      "compositePrimaryKeys": {},
      "uniqueConstraints": {},
      "checkConstraints": {}
    },
    "user": {
      "name": "user",
      "columns": {
        "id": {
          "name": "id",
          "type": "text",
          "primaryKey": true,
          "notNull": true,
          "autoincrement": false
        },
        "name": {
          "name": "name",
          "type": "text",
          "primaryKey": false,
          "notNull": false,
          "autoincrement": false
        },
        "email": {
          "name": "email",
          "type": "text",
          "primaryKey": false,
          "notNull": true,
          "autoincrement": false
        },
        "emailVerified": {
          "name": "emailVerified",
          "type": "integer",
          "primaryKey": false,
          "notNull": false,
          "autoincrement": false
        },
        "image": {
          "name": "image",
          "type": "text",
          "primaryKey": false,
          "notNull": false,
          "autoincrement": false
        },
        "displayName": {
          "name": "displayName",
          "type": "text",
          "primaryKey": false,
          "notNull": false,
          "autoincrement": false
        },
        "mu": {
          "name": "mu",
          "type": "real",
          "primaryKey": false,
          "notNull": true,
          "autoincrement": false,
          "default": 25
        },
        "sigma": {
          "name": "sigma",
          "type": "real",
          "primaryKey": false,
          "notNull": true,
          "autoincrement": false,
          "default": 8.333333333333334
        },
        "createdAt": {
          "name": "createdAt",
          "type": "integer",
          "primaryKey": false,
          "notNull": true,
          "autoincrement": false,
          "default": "(unixepoch() * 1000)"
        }
      },
      "indexes": {
        "user_email_unique": {
          "name": "user_email_unique",
          "columns": [
            "email"
          ],
          "isUnique": true
        }
      },
      "foreignKeys": {},
      "compositePrimaryKeys": {},
      "uniqueConstraints": {},
      "checkConstraints": {}
    },
    "verificationToken": {
      "name": "verificationToken",
      "columns": {
        "identifier": {
          "name": "identifier",
          "type": "text",
          "primaryKey": false,
          "notNull": true,
          "autoincrement": false
        },
        "token": {
          "name": "token",
          "type": "text",
          "primaryKey": false,
          "notNull": true,
          "autoincrement": false
        },
        "expires": {
          "name": "expires",
          "type": "integer",
          "primaryKey": false,
          "notNull": true,
          "autoincrement": false
        }
      },
      "indexes": {},
      "foreignKeys": {},
      "compositePrimaryKeys": {
        "verificationToken_identifier_token_pk": {
          "columns": [
            "identifier",
            "token"
          ],
          "name": "verificationToken_identifier_token_pk"
        }
      },
      "uniqueConstraints": {},
      "checkConstraints": {}
    }
  },
  "views": {},
  "enums": {},
  "_meta": {
    "schemas": {},
    "tables": {},
    "columns": {}
  },
  "internal": {
    "indexes": {}
  }
}